pytest_tesults.py
pytest_tesults-1.8.0.dist-info/LICENSE
pytest_tesults-1.8.0.dist-info/METADATA
pytest_tesults-1.8.0.dist-info/WHEEL
pytest_tesults-1.8.0.dist-info/entry_points.txt
pytest_tesults-1.8.0.dist-info/top_level.txt
pytest_tesults-1.8.0.dist-info/RECORD
