Metadata-Version: 2.1
Name: pytest-tesults
Version: 1.8.0
Summary: Tesults plugin for pytest
Home-page: https://www.tesults.com/docs/pytest
Author: Tesults
Author-email: help@tesults.com
Maintainer: Tesults
Maintainer-email: help@tesults.com
License: MIT
Keywords: tesults test results automation automated dashboard reporting pytest plugin
Classifier: Framework :: Pytest
Classifier: Development Status :: 5 - Production/Stable
Classifier: Intended Audience :: Developers
Classifier: Framework :: Pytest
Classifier: Topic :: Software Development :: Testing
Classifier: Programming Language :: Python
Classifier: Programming Language :: Python :: 2
Classifier: Programming Language :: Python :: 2.7
Classifier: Programming Language :: Python :: 3
Classifier: Programming Language :: Python :: 3.4
Classifier: Programming Language :: Python :: 3.5
Classifier: Programming Language :: Python :: 3.6
Classifier: Programming Language :: Python :: 3.7
Classifier: Programming Language :: Python :: Implementation :: CPython
Classifier: Programming Language :: Python :: Implementation :: PyPy
Classifier: Operating System :: OS Independent
Classifier: License :: OSI Approved :: MIT License
Requires-Python: >=2.7
License-File: LICENSE
Requires-Dist: pytest >=3.5.0
Requires-Dist: tesults
